gw2pvo/__init__.py
gw2pvo/__main__.py
gw2pvo/average.py
gw2pvo/ds_api.py
gw2pvo/gw_api.py
gw2pvo/gw_csv.py
gw2pvo/netatmo_api.py
gw2pvo/pvo_api.py
gw2pvo-1.3.6.dist-info/LICENSE
gw2pvo-1.3.6.dist-info/METADATA
gw2pvo-1.3.6.dist-info/WHEEL
gw2pvo-1.3.6.dist-info/entry_points.txt
gw2pvo-1.3.6.dist-info/top_level.txt
gw2pvo-1.3.6.dist-info/RECORD
