Metadata-Version: 2.1
Name: gw2pvo
Version: 1.3.6
Summary: Upload GoodWe inverter readings to PVOutput.org
Home-page: https://github.com/markruys/gw2pvo
Author: Mark Ruys
Author-email: mark@paracas.nl
License: MIT
Keywords: goodwe pvoutput solar
Platform: UNKNOWN
Classifier: Development Status :: 4 - Beta
Classifier: Intended Audience :: End Users/Desktop
Classifier: Topic :: System :: Monitoring
Classifier: License :: OSI Approved :: MIT License
Classifier: Programming Language :: Python :: 3
Classifier: Programming Language :: Python :: 3.6
Classifier: Programming Language :: Python :: 3.7
Classifier: Programming Language :: Python :: 3.8
Requires-Python: >=3.6
Requires-Dist: astral (>=2)
Requires-Dist: requests
Requires-Dist: oauthlib
Requires-Dist: requests-oauthlib
